Metadata-Version: 2.1
Name: project-11Team-GoIt
Version: 1.11
Summary: AssistantBot include adressbook and notes
Home-page: https://github.com/osandrey/GoIt_Team_11_Project/tree/testmyadressbook
Author: Dima, Inna, Serhiy, Andrey
Author-email: dima63475@gmail.com
License: UA
Platform: UNKNOWN
